azure/monitor/query/__init__.py
azure/monitor/query/_enums.py
azure/monitor/query/_exceptions.py
azure/monitor/query/_helpers.py
azure/monitor/query/_logs_query_client.py
azure/monitor/query/_metrics_client.py
azure/monitor/query/_metrics_query_client.py
azure/monitor/query/_models.py
azure/monitor/query/_version.py
azure/monitor/query/py.typed
azure/monitor/query/_generated/__init__.py
azure/monitor/query/_generated/_client.py
azure/monitor/query/_generated/_configuration.py
azure/monitor/query/_generated/_patch.py
azure/monitor/query/_generated/_serialization.py
azure/monitor/query/_generated/aio/__init__.py
azure/monitor/query/_generated/aio/_client.py
azure/monitor/query/_generated/aio/_configuration.py
azure/monitor/query/_generated/aio/_patch.py
azure/monitor/query/_generated/aio/operations/__init__.py
azure/monitor/query/_generated/aio/operations/_operations.py
azure/monitor/query/_generated/aio/operations/_patch.py
azure/monitor/query/_generated/metrics/__init__.py
azure/monitor/query/_generated/metrics/_client.py
azure/monitor/query/_generated/metrics/_configuration.py
azure/monitor/query/_generated/metrics/_patch.py
azure/monitor/query/_generated/metrics/_serialization.py
azure/monitor/query/_generated/metrics/aio/__init__.py
azure/monitor/query/_generated/metrics/aio/_client.py
azure/monitor/query/_generated/metrics/aio/_configuration.py
azure/monitor/query/_generated/metrics/aio/_patch.py
azure/monitor/query/_generated/metrics/aio/operations/__init__.py
azure/monitor/query/_generated/metrics/aio/operations/_operations.py
azure/monitor/query/_generated/metrics/aio/operations/_patch.py
azure/monitor/query/_generated/metrics/batch/__init__.py
azure/monitor/query/_generated/metrics/batch/_client.py
azure/monitor/query/_generated/metrics/batch/_configuration.py
azure/monitor/query/_generated/metrics/batch/_patch.py
azure/monitor/query/_generated/metrics/batch/_serialization.py
azure/monitor/query/_generated/metrics/batch/aio/__init__.py
azure_monitor_query-1.4.0.dist-info/LICENSE
azure_monitor_query-1.4.0.dist-info/METADATA
azure_monitor_query-1.4.0.dist-info/WHEEL
azure_monitor_query-1.4.0.dist-info/top_level.txt
azure_monitor_query-1.4.0.dist-info/RECORD
